lively_tk-1.1.0.dist-info/METADATA
lively_tk-1.1.0.dist-info/WHEEL
lively_tk-1.1.0.dist-info/license_files/LICENSE
lively/__init__.py
lively/lively.abi3.so
lively_tk-1.1.0.dist-info/RECORD
