Metadata-Version: 2.1
Name: lively-tk
Version: 1.1.0
Classifier: Programming Language :: Rust
Classifier: Programming Language :: Python :: Implementation :: CPython
Classifier: Programming Language :: Python :: Implementation :: PyPy
License-File: LICENSE
Summary: A highly configurable toolkit for commanding robots in mixed modalities with liveliness.
Home-Page: https://wisc-hci.github.io/lively/
Author: andrewjschoen <schoen.andrewj@gmail.com>, djrakita <djrakita@gmail.com>
Author-email: andrewjschoen <schoen.andrewj@gmail.com>, djrakita <djrakita@gmail.com>
License: MIT
Requires-Python: >=3.7
Project-URL: Source Code, https://github.com/Wisc-HCI/lively
